epiphancloud/__init__.py
epiphancloud/access.py
epiphancloud/api.py
epiphancloud/devices.py
epiphancloud/exceptions.py
epiphancloud/models/__init__.py
epiphancloud/models/desired_state.py
epiphancloud/models/device.py
epiphancloud/models/settings.py
epiphancloud-2.0.2.dist-info/LICENSE.txt
epiphancloud-2.0.2.dist-info/METADATA
epiphancloud-2.0.2.dist-info/WHEEL
epiphancloud-2.0.2.dist-info/top_level.txt
epiphancloud-2.0.2.dist-info/RECORD
