Metadata-Version: 2.1
Name: epiphancloud
Version: 2.0.2
Summary: Python wrappers for Epiphan Cloud public API
Home-page: https://github.com/epiphan-video/epiphancloud_api
Author: Vadim Kalinskiy
Author-email: vkalinsky@epiphan.com
License: UNKNOWN
Project-URL: Documentation, https://epiphan-video.github.io/epiphancloud_api
Platform: UNKNOWN
Classifier: Programming Language :: Python :: 3
Classifier: License :: OSI Approved :: MIT License
Classifier: Operating System :: OS Independent
Requires-Python: >=3.6
License-File: LICENSE.txt
Requires-Dist: build (==0.7.0)
Requires-Dist: certifi (==2021.10.8)
Requires-Dist: charset-normalizer (==2.0.10)
Requires-Dist: idna (==3.3)
Requires-Dist: packaging (==21.3)
Requires-Dist: pep517 (==0.12.0)
Requires-Dist: pyparsing (==3.0.6)
Requires-Dist: requests (==2.27.0)
Requires-Dist: requests-toolbelt (==0.9.1)
Requires-Dist: tomli (==2.0.0)
Requires-Dist: urllib3 (==1.26.7)
